Workbook

Sheet Resumen
A1: Plan de Pruebas — Hipoteca Joven (4013) · Seguimiento de ejecución
A3: Indicadores globales (pasos) | D3: Estado | E3: Pasos
A4: Total de pasos | B4: =COUNTA('Casos de prueba'!D2:D170) | D4: Pendiente | E4: =COUNTIF('Casos de prueba'!J2:J170,"Pendiente")
A5: Pendientes | B5: =COUNTIF('Casos de prueba'!J2:J170,"Pendiente") | D5: OK | E5: =COUNTIF('Casos de prueba'!J2:J170,"OK")
A6: OK | B6: =COUNTIF('Casos de prueba'!J2:J170,"OK") | D6: KO | E6: =COUNTIF('Casos de prueba'!J2:J170,"KO")
A7: KO (incidencias) | B7: =COUNTIF('Casos de prueba'!J2:J170,"KO")
A8: % Avance (ejecutados) | B8: =IFERROR((COUNTIF('Casos de prueba'!J2:J170,"OK")+COUNTIF('Casos de prueba'!J2:J170,"KO"))/COUNTA('Casos de prueba'!D2:D170),0)
A9: % Éxito (OK/ejecutados) | B9: =IFERROR(COUNTIF('Casos de prueba'!J2:J170,"OK")/(COUNTIF('Casos de prueba'!J2:J170,"OK")+COUNTIF('Casos de prueba'!J2:J170,"KO")),0)
A10: Bugs referenciados | B10: =SUMPRODUCT(--('Casos de prueba'!K2:K170<>""))
A12: Desglose por módulo
A13: Módulo | B13: Total | C13: Pendiente | D13: OK | E13: KO | F13: % Avance
A14: Pantalla de alta de expediente | B14: =COUNTIF('Casos de prueba'!$A$2:$A$170,A14) | C14: =COUNTIFS('Casos de prueba'!$A$2:$A$170,A14,'Casos de prueba'!$J$2:$J$170,"Pendiente") | D14: =COUNTIFS('Casos de prueba'!$A$2:$A$170,A14,'Casos de prueba'!$J$2:$J$170,"OK") | E14: =COUNTIFS('Casos de prueba'!$A$2:$A$170,A14,'Casos de prueba'!$J$2:$J$170,"KO") | F14: =IFERROR((D14+E14)/B14,0)
A15: Simulador de alta | B15: =COUNTIF('Casos de prueba'!$A$2:$A$170,A15) | C15: =COUNTIFS('Casos de prueba'!$A$2:$A$170,A15,'Casos de prueba'!$J$2:$J$170,"Pendiente") | D15: =COUNTIFS('Casos de prueba'!$A$2:$A$170,A15,'Casos de prueba'!$J$2:$J$170,"OK") | E15: =COUNTIFS('Casos de prueba'!$A$2:$A$170,A15,'Casos de prueba'!$J$2:$J$170,"KO") | F15: =IFERROR((D15+E15)/B15,0)
A16: Pantalla de pre-aprobación | B16: =COUNTIF('Casos de prueba'!$A$2:$A$170,A16) | C16: =COUNTIFS('Casos de prueba'!$A$2:$A$170,A16,'Casos de prueba'!$J$2:$J$170,"Pendiente") | D16: =COUNTIFS('Casos de prueba'!$A$2:$A$170,A16,'Casos de prueba'!$J$2:$J$170,"OK") | E16: =COUNTIFS('Casos de prueba'!$A$2:$A$170,A16,'Casos de prueba'!$J$2:$J$170,"KO") | F16: =IFERROR((D16+E16)/B16,0)
A17: Pantalla de datos del expediente | B17: =COUNTIF('Casos de prueba'!$A$2:$A$170,A17) | C17: =COUNTIFS('Casos de prueba'!$A$2:$A$170,A17,'Casos de prueba'!$J$2:$J$170,"Pendiente") | D17: =COUNTIFS('Casos de prueba'!$A$2:$A$170,A17,'Casos de prueba'!$J$2:$J$170,"OK") | E17: =COUNTIFS('Casos de prueba'!$A$2:$A$170,A17,'Casos de prueba'!$J$2:$J$170,"KO") | F17: =IFERROR((D17+E17)/B17,0)
A18: Pantalla datos de Pre-aprobación | B18: =COUNTIF('Casos de prueba'!$A$2:$A$170,A18) | C18: =COUNTIFS('Casos de prueba'!$A$2:$A$170,A18,'Casos de prueba'!$J$2:$J$170,"Pendiente") | D18: =COUNTIFS('Casos de prueba'!$A$2:$A$170,A18,'Casos de prueba'!$J$2:$J$170,"OK") | E18: =COUNTIFS('Casos de prueba'!$A$2:$A$170,A18,'Casos de prueba'!$J$2:$J$170,"KO") | F18: =IFERROR((D18+E18)/B18,0)
A19: Modificación del préstamo (post-alta) | B19: =COUNTIF('Casos de prueba'!$A$2:$A$170,A19) | C19: =COUNTIFS('Casos de prueba'!$A$2:$A$170,A19,'Casos de prueba'!$J$2:$J$170,"Pendiente") | D19: =COUNTIFS('Casos de prueba'!$A$2:$A$170,A19,'Casos de prueba'!$J$2:$J$170,"OK") | E19: =COUNTIFS('Casos de prueba'!$A$2:$A$170,A19,'Casos de prueba'!$J$2:$J$170,"KO") | F19: =IFERROR((D19+E19)/B19,0)
A20: Pantalla de intervinientes | B20: =COUNTIF('Casos de prueba'!$A$2:$A$170,A20) | C20: =COUNTIFS('Casos de prueba'!$A$2:$A$170,A20,'Casos de prueba'!$J$2:$J$170,"Pendiente") | D20: =COUNTIFS('Casos de prueba'!$A$2:$A$170,A20,'Casos de prueba'!$J$2:$J$170,"OK") | E20: =COUNTIFS('Casos de prueba'!$A$2:$A$170,A20,'Casos de prueba'!$J$2:$J$170,"KO") | F20: =IFERROR((D20+E20)/B20,0)
A21: Revisión de diferencia de ingresos | B21: =COUNTIF('Casos de prueba'!$A$2:$A$170,A21) | C21: =COUNTIFS('Casos de prueba'!$A$2:$A$170,A21,'Casos de prueba'!$J$2:$J$170,"Pendiente") | D21: =COUNTIFS('Casos de prueba'!$A$2:$A$170,A21,'Casos de prueba'!$J$2:$J$170,"OK") | E21: =COUNTIFS('Casos de prueba'!$A$2:$A$170,A21,'Casos de prueba'!$J$2:$J$170,"KO") | F21: =IFERROR((D21+E21)/B21,0)
A22: Llamadas a Modellica | B22: =COUNTIF('Casos de prueba'!$A$2:$A$170,A22) | C22: =COUNTIFS('Casos de prueba'!$A$2:$A$170,A22,'Casos de prueba'!$J$2:$J$170,"Pendiente") | D22: =COUNTIFS('Casos de prueba'!$A$2:$A$170,A22,'Casos de prueba'!$J$2:$J$170,"OK") | E22: =COUNTIFS('Casos de prueba'!$A$2:$A$170,A22,'Casos de prueba'!$J$2:$J$170,"KO") | F22: =IFERROR((D22+E22)/B22,0)
A23: Alta/Actualización expedientes en Gestoría | B23: =COUNTIF('Casos de prueba'!$A$2:$A$170,A23) | C23: =COUNTIFS('Casos de prueba'!$A$2:$A$170,A23,'Casos de prueba'!$J$2:$J$170,"Pendiente") | D23: =COUNTIFS('Casos de prueba'!$A$2:$A$170,A23,'Casos de prueba'!$J$2:$J$170,"OK") | E23: =COUNTIFS('Casos de prueba'!$A$2:$A$170,A23,'Casos de prueba'!$J$2:$J$170,"KO") | F23: =IFERROR((D23+E23)/B23,0)
A24: Servicios WF (Expone WF) | B24: =COUNTIF('Casos de prueba'!$A$2:$A$170,A24) | C24: =COUNTIFS('Casos de prueba'!$A$2:$A$170,A24,'Casos de prueba'!$J$2:$J$170,"Pendiente") | D24: =COUNTIFS('Casos de prueba'!$A$2:$A$170,A24,'Casos de prueba'!$J$2:$J$170,"OK") | E24: =COUNTIFS('Casos de prueba'!$A$2:$A$170,A24,'Casos de prueba'!$J$2:$J$170,"KO") | F24: =IFERROR((D24+E24)/B24,0)
A25: Exportaciones | B25: =COUNTIF('Casos de prueba'!$A$2:$A$170,A25) | C25: =COUNTIFS('Casos de prueba'!$A$2:$A$170,A25,'Casos de prueba'!$J$2:$J$170,"Pendiente") | D25: =COUNTIFS('Casos de prueba'!$A$2:$A$170,A25,'Casos de prueba'!$J$2:$J$170,"OK") | E25: =COUNTIFS('Casos de prueba'!$A$2:$A$170,A25,'Casos de prueba'!$J$2:$J$170,"KO") | F25: =IFERROR((D25+E25)/B25,0)
... A29: Regresión | B29: =COUNTIF('Casos de prueba'!$A$2:$A$170,A29) | C29: =COUNTIFS('Casos de prueba'!$A$2:$A$170,A29,'Casos de prueba'!$J$2:$J$170,"Pendiente") | D29: =COUNTIFS('Casos de prueba'!$A$2:$A$170,A29,'Casos de prueba'!$J$2:$J$170,"OK") | E29: =COUNTIFS('Casos de prueba'!$A$2:$A$170,A29,'Casos de prueba'!$J$2:$J$170,"KO") | F29: =IFERROR((D29+E29)/B29,0)
A32: Desglose por caso
A33: ID-CASO | B33: Caso | C33: Total | D33: Pend. | E33: OK | F33: KO | G33: % Avance | H33: Estado caso
A34: CU-01 | B34: Nuevos campos en el formulario | C34: =COUNTIF('Casos de prueba'!$B$2:$B$170,A34) | D34: =COUNTIFS('Casos de prueba'!$B$2:$B$170,A34,'Casos de prueba'!$J$2:$J$170,"Pendiente") | E34: =COUNTIFS('Casos de prueba'!$B$2:$B$170,A34,'Casos de prueba'!$J$2:$J$170,"OK") | F34: =COUNTIFS('Casos de prueba'!$B$2:$B$170,A34,'Casos de prueba'!$J$2:$J$170,"KO") | G34: =IFERROR((E34+F34)/C34,0) | H34: =IF(F34>0,"KO",IF(D34>0,"En curso","OK"))
A35: CU-02 | B35: Integración con datos externos | C35: =COUNTIF('Casos de prueba'!$B$2:$B$170,A35) | D35: =COUNTIFS('Casos de prueba'!$B$2:$B$170,A35,'Casos de prueba'!$J$2:$J$170,"Pendiente") | E35: =COUNTIFS('Casos de prueba'!$B$2:$B$170,A35,'Casos de prueba'!$J$2:$J$170,"OK") | F35: =COUNTIFS('Casos de prueba'!$B$2:$B$170,A35,'Casos de prueba'!$J$2:$J$170,"KO") | G35: =IFERROR((E35+F35)/C35,0) | H35: =IF(F35>0,"KO",IF(D35>0,"En curso","OK"))
A36: CU-03 | B36: Evaluación INIT y navegación | C36: =COUNTIF('Casos de prueba'!$B$2:$B$170,A36) | D36: =COUNTIFS('Casos de prueba'!$B$2:$B$170,A36,'Casos de prueba'!$J$2:$J$170,"Pendiente") | E36: =COUNTIFS('Casos de prueba'!$B$2:$B$170,A36,'Casos de prueba'!$J$2:$J$170,"OK") | F36: =COUNTIFS('Casos de prueba'!$B$2:$B$170,A36,'Casos de prueba'!$J$2:$J$170,"KO") | G36: =IFERROR((E36+F36)/C36,0) | H36: =IF(F36>0,"KO",IF(D36>0,"En curso","OK"))
A37: CU-04 | B37: Bloques de datos y pop-ups de edición | C37: =COUNTIF('Casos de prueba'!$B$2:$B$170,A37) | D37: =COUNTIFS('Casos de prueba'!$B$2:$B$170,A37,'Casos de prueba'!$J$2:$J$170,"Pendiente") | E37: =COUNTIFS('Casos de prueba'!$B$2:$B$170,A37,'Casos de prueba'!$J$2:$J$170,"OK") | F37: =COUNTIFS('Casos de prueba'!$B$2:$B$170,A37,'Casos de prueba'!$J$2:$J$170,"KO") | G37: =IFERROR((E37+F37)/C37,0) | H37: =IF(F37>0,"KO",IF(D37>0,"En curso","OK"))
A38: CU-05 | B38: Evaluación PRE | C38: =COUNTIF('Casos de prueba'!$B$2:$B$170,A38) | D38: =COUNTIFS('Casos de prueba'!$B$2:$B$170,A38,'Casos de prueba'!$J$2:$J$170,"Pendiente") | E38: =COUNTIFS('Casos de prueba'!$B$2:$B$170,A38,'Casos de prueba'!$J$2:$J$170,"OK") | F38: =COUNTIFS('Casos de prueba'!$B$2:$B$170,A38,'Casos de prueba'!$J$2:$J$170,"KO") | G38: =IFERROR((E38+F38)/C38,0) | H38: =IF(F38>0,"KO",IF(D38>0,"En curso","OK"))
A39: CU-06 | B39: Flag SOLICITAR_DATOS_INTERVINIENTES | C39: =COUNTIF('Casos de prueba'!$B$2:$B$170,A39) | D39: =COUNTIFS('Casos de prueba'!$B$2:$B$170,A39,'Casos de prueba'!$J$2:$J$170,"Pendiente") | E39: =COUNTIFS('Casos de prueba'!$B$2:$B$170,A39,'Casos de prueba'!$J$2:$J$170,"OK") | F39: =COUNTIFS('Casos de prueba'!$B$2:$B$170,A39,'Casos de prueba'!$J$2:$J$170,"KO") | G39: =IFERROR((E39+F39)/C39,0) | H39: =IF(F39>0,"KO",IF(D39>0,"En curso","OK"))
A40: CU-07 | B40: Evaluación FINAL y visualización de ofertas | C40: =COUNTIF('Casos de prueba'!$B$2:$B$170,A40) | D40: =COUNTIFS('Casos de prueba'!$B$2:$B$170,A40,'Casos de prueba'!$J$2:$J$170,"Pendiente") | E40: =COUNTIFS('Casos de prueba'!$B$2:$B$170,A40,'Casos de prueba'!$J$2:$J$170,"OK") | F40: =COUNTIFS('Casos de prueba'!$B$2:$B$170,A40,'Casos de prueba'!$J$2:$J$170,"KO") | G40: =IFERROR((E40+F40)/C40,0) | H40: =IF(F40>0,"KO",IF(D40>0,"En curso","OK"))
A41: CU-08 | B41: Ajuste automático de importes y plazos | C41: =COUNTIF('Casos de prueba'!$B$2:$B$170,A41) | D41: =COUNTIFS('Casos de prueba'!$B$2:$B$170,A41,'Casos de prueba'!$J$2:$J$170,"Pendiente") | E41: =COUNTIFS('Casos de prueba'!$B$2:$B$170,A41,'Casos de prueba'!$J$2:$J$170,"OK") | F41: =COUNTIFS('Casos de prueba'!$B$2:$B$170,A41,'Casos de prueba'!$J$2:$J$170,"KO") | G41: =IFERROR((E41+F41)/C41,0) | H41: =IF(F41>0,"KO",IF(D41>0,"En curso","OK"))
A42: CU-09 | B42: Pantalla de pre-aprobación | C42: =COUNTIF('Casos de prueba'!$B$2:$B$170,A42) | D42: =COUNTIFS('Casos de prueba'!$B$2:$B$170,A42,'Casos de prueba'!$J$2:$J$170,"Pendiente") | E42: =COUNTIFS('Casos de prueba'!$B$2:$B$170,A42,'Casos de prueba'!$J$2:$J$170,"OK") | F42: =COUNTIFS('Casos de prueba'!$B$2:$B$170,A42,'Casos de prueba'!$J$2:$J$170,"KO") | G42: =IFERROR((E42+F42)/C42,0) | H42: =IF(F42>0,"KO",IF(D42>0,"En curso","OK"))
A43: CU-10 | B43: Pantalla de datos del expediente | C43: =COUNTIF('Casos de prueba'!$B$2:$B$170,A43) | D43: =COUNTIFS('Casos de prueba'!$B$2:$B$170,A43,'Casos de prueba'!$J$2:$J$170,"Pendiente") | E43: =COUNTIFS('Casos de prueba'!$B$2:$B$170,A43,'Casos de prueba'!$J$2:$J$170,"OK") | F43: =COUNTIFS('Casos de prueba'!$B$2:$B$170,A43,'Casos de prueba'!$J$2:$J$170,"KO") | G43: =IFERROR((E43+F43)/C43,0) | H43: =IF(F43>0,"KO",IF(D43>0,"En curso","OK"))
A44: CU-11 | B44: Pantalla datos de Pre-aprobación | C44: =COUNTIF('Casos de prueba'!$B$2:$B$170,A44) | D44: =COUNTIFS('Casos de prueba'!$B$2:$B$170,A44,'Casos de prueba'!$J$2:$J$170,"Pendiente") | E44: =COUNTIFS('Casos de prueba'!$B$2:$B$170,A44,'Casos de prueba'!$J$2:$J$170,"OK") | F44: =COUNTIFS('Casos de prueba'!$B$2:$B$170,A44,'Casos de prueba'!$J$2:$J$170,"KO") | G44: =IFERROR((E44+F44)/C44,0) | H44: =IF(F44>0,"KO",IF(D44>0,"En curso","OK"))
A45: CU-12 | B45: Modificación del préstamo (post-alta) | C45: =COUNTIF('Casos de prueba'!$B$2:$B$170,A45) | D45: =COUNTIFS('Casos de prueba'!$B$2:$B$170,A45,'Casos de prueba'!$J$2:$J$170,"Pendiente") | E45: =COUNTIFS('Casos de prueba'!$B$2:$B$170,A45,'Casos de prueba'!$J$2:$J$170,"OK") | F45: =COUNTIFS('Casos de prueba'!$B$2:$B$170,A45,'Casos de prueba'!$J$2:$J$170,"KO") | G45: =IFERROR((E45+F45)/C45,0) | H45: =IF(F45>0,"KO",IF(D45>0,"En curso","OK"))
... A62: CU-26 | B62: Regresión | C62: =COUNTIF('Casos de prueba'!$B$2:$B$170,A62) | D62: =COUNTIFS('Casos de prueba'!$B$2:$B$170,A62,'Casos de prueba'!$J$2:$J$170,"Pendiente") | E62: =COUNTIFS('Casos de prueba'!$B$2:$B$170,A62,'Casos de prueba'!$J$2:$J$170,"OK") | F62: =COUNTIFS('Casos de prueba'!$B$2:$B$170,A62,'Casos de prueba'!$J$2:$J$170,"KO") | G62: =IFERROR((E62+F62)/C62,0) | H62: =IF(F62>0,"KO",IF(D62>0,"En curso","OK"))

Sheet Casos de prueba
A1: Módulo | B1: ID-CASO | C1: Caso | D1: Paso | E1: Área | F1: Descripción | G1: Condiciones / Datos | H1: Resultado esperado | I1: Resultado obtenido | J1: Estado | K1: Bugs | L1: Evidencia | M1: Asignado a
A2: Pantalla de alta de expediente | B2: CU-01 | C2: Nuevos campos en el formulario | D2: CU-01-1 | E2: Alta > Campos | F2: El campo tipoAlta aparece en el formulario de alta | G2: Acceder a pantalla de alta | H2: Campo visible con lista de valores admitidos (al menos ALTA_NUEVA y NOVACION) | J2: Pendiente
A3: Pantalla de alta de expediente | B3: CU-01 | C3: Nuevos campos en el formulario | D3: CU-01-2 | E3: Alta > Campos | F3: El campo finalidad (1ª / 2ª vivienda) aparece en el formulario | G3: Acceder a pantalla de alta | H3: Campo visible con al menos "1ª vivienda" y "2ª vivienda" | J3: Pendiente
A4: Pantalla de alta de expediente | B4: CU-01 | C4: Nuevos campos en el formulario | D4: CU-01-3 | E4: Alta > Campos | F4: El campo primeraViviendaHabitual (Sí/No) aparece en el formulario | G4: Acceder a pantalla de alta | H4: Campo visible; valores Sí / No | J4: Pendiente
A5: Pantalla de alta de expediente | B5: CU-01 | C5: Nuevos campos en el formulario | D5: CU-01-4 | E5: Alta > Campos | F5: El campo tipoVivienda (nueva / segunda mano) aparece en el formulario | G5: Acceder a pantalla de alta | H5: Campo visible con los valores correspondientes | J5: Pendiente
A6: Pantalla de alta de expediente | B6: CU-01 | C6: Nuevos campos en el formulario | D6: CU-01-5 | E6: Alta > Campos | F6: El campo comunidadAutonoma aparece en el formulario | G6: Acceder a pantalla de alta | H6: Campo visible con la lista completa de CCAA | J6: Pendiente
A7: Pantalla de alta de expediente | B7: CU-01 | C7: Nuevos campos en el formulario | D7: CU-01-6 | E7: Alta > Campos | F7: El campo ¿tienes elegida ya la vivienda? aparece en el formulario | G7: Acceder a pantalla de alta | H7: Campo visible con valores Sí / No | J7: Pendiente
A8: Pantalla de alta de expediente | B8: CU-01 | C8: Nuevos campos en el formulario | D8: CU-01-7 | E8: Alta > Campos | F8: El campo Importe de la vivienda aparece en el formulario | G8: Acceder a pantalla de alta | H8: Campo visible con valor numérico | J8: Pendiente
A9: Pantalla de alta de expediente | B9: CU-01 | C9: Nuevos campos en el formulario | D9: CU-01-8 | E9: Alta > Validación | F9: Los nuevos campos son obligatorios; el formulario no avanza si alguno falta | G9: Dejar uno o varios campos sin informar e intentar continuar | H9: Se muestra error de validación e impide avanzar al simulador | J9: Pendiente
A10: Pantalla de alta de expediente | B10: CU-02 | C10: Integración con datos externos | D10: CU-02-1 | E10: Alta > CRS | F10: edadT1 se obtiene del servicio CRS al informar el número de cliente | G10: Número de cliente válido en CRS | H10: El campo edadT1 se rellena automáticamente desde la fecha de nacimiento devuelta por CRS | J10: Pendiente
A11: Pantalla de alta de expediente | B11: CU-02 | C11: Integración con datos externos | D11: CU-02-2 | E11: Alta > Riesgos | F11: domiciliaNominaT1 se obtiene del fichero de riesgos | G11: Número de cliente con datos en fichero de riesgos | H11: El campo interno domiciliaNominaT1 queda a 1 o 0 según el fichero | J11: Pendiente
A12: Pantalla de alta de expediente | B12: CU-02 | C12: Integración con datos externos | D12: CU-02-3 | E12: Alta > Riesgos | F12: antiguedadT1 se obtiene del fichero de riesgos | G12: Número de cliente con datos en fichero de riesgos | H12: El campo interno antiguedadT1 queda calculado en meses según la fecha ANTIGUEDAD_DT del fichero | J12: Pendiente
A13: Pantalla de alta de expediente | B13: CU-02 | C13: Integración con datos externos | D13: CU-02-4 | E13: Alta > CRS | F13: antiguedadT1 se obtiene por CRS porque cliente no está en fichero | G13: Número de cliente SIN datos en fichero de riesgos | H13: El campo interno antiguedadT1 se obtiene de CRS calculado en meses según la fecha fecha_Alta | J13: Pendiente
... A170: Regresión | B170: CU-26 | C170: Regresión | D170: CU-26-8 | E170: Regresión | F170: La pantalla de datos del expediente carga sin errores para expedientes creados antes del despliegue | G170: Abrir datos de un expediente antiguo | H170: La pantalla carga; el campo primeraViviendaHabitualFl aparece vacío o N/A sin provocar error | J170: Pendiente
